{"name":"mc,免费","slug":"mc-免费","count":1,"postlist":[{"title":"MC（Java）启动器免费分享","uid":"1a922cd22d12a800668acd8193b51aa5","slug":"MC（Java）启动器免费分享","date":"2023-11-26T10:17:27.000Z","updated":"2023-11-26T10:17:56.557Z","comments":true,"path":"api/articles/MC（Java）启动器免费分享.json","keywords":null,"cover":[],"text":"MCjava版启动器免费分享，与教程 介绍启动器1. PCL2 （Plain Craft Launcher 2）作者龙腾猫跃 介绍1.官方 2.个人 个人感觉P...","permalink":"/post/MC（Java）启动器免费分享","photos":[],"count_time":{"symbolsCount":622,"symbolsTime":"1 mins."},"categories":[],"tags":[{"name":"mc,免费","slug":"mc-免费","count":1,"path":"api/tags/mc-免费.json"}],"author":{"name":"Aser","slug":"blog-author","avatar":"https://avatars.githubusercontent.com/u/152001245?s=400&v=4","link":"/","description":"一个游戏迷，没事开发点东西，喜欢玩mc，热爱分享资源","socials":{"github":"","twitter":"","stackoverflow":"","wechat":"","qq":"","weibo":"","zhihu":"","csdn":"","juejin":"","customs":{}}},"feature":true}]}